{
    "BomberAltitude": 550,
    "BomberSpeed": 10,
    "NumOfBombs": 20,
    "Notifications": 0,
    "EnableShips": 0,
    "EnableSubmarine": 0,
    "EnableAndula": 0,
    "EnableMig21": 0,
    "EnableUFO": 0,
    "EnableMi24": 0,
    "Interval": 45.0,
    "SubmarineInterval": 45.0,
    "BoatInterval": 45.0,
    "AndulaInterval": 60.0,
    "Mig21Interval": 120.0,
    "UFOInterval": 120.0,
    "Mi24Interval": 40.0,
    "AirRaidLocations": [
        {
            "name": "Old Town",
            "sirenpos": "1765 24 9018",
            "target": "1765 0 9018",
            "type": "normal"
        },
        {
            "name": "Westbrook",
            "sirenpos": "3280 24 6500",
            "target": "3280 0 6500",
            "type": "normal"
        },
        {
            "name": "Paris Island",
            "sirenpos": "2794 24 3709",
            "target": "2794 0 3709",
            "type": "normal"
        },
        {
            "name": "Hazeland",
            "sirenpos": "4556 24 2597",
            "target": "4556 0 2597",
            "type": "normal"
        },
        {
            "name": "Krasnostav",
            "sirenpos": "12159 24 12583",
            "target": "12159 0 12583",
            "type": "normal"
        },
        {
            "name": "Stonington",
            "sirenpos": "6951 24 1723",
            "target": "6951 0 1723",
            "type": "normal"
        },
        {
            "name": "Airfield",
            "sirenpos": "5493 24 3493",
            "target": "5493 0 3493",
            "type": "normal"
        },
        {
            "name": "Warren Cove",
            "sirenpos": "6934 24 5472",
            "target": "6934 0 5472",
            "type": "normal"
        },
        {
            "name": "Novy Sobor",
            "sirenpos": "7436 24 7720",
            "target": "7436 0 7720",
            "type": "normal"
        },
        {
            "name": "Old Field",
            "sirenpos": "6133 24 7009",
            "target": "6133 0 7009",
            "type": "normal"
        },
        {
            "name": "Mountain View",
            "sirenpos": "7195 24 8354",
            "target": "7195 0 8354",
            "type": "normal"
        },
        {
            "name": "Ocean View",
            "sirenpos": "10179 24 4720",
            "target": "10179 0 4720",
            "type": "normal"
        },
        {
            "name": "Waldoboro",
            "sirenpos": "8750 24 8809",
            "target": "8750 0 8809",
            "type": "normal"
        },
        {
            "name": "East Brook",
            "sirenpos": "10451 24 7915",
            "target": "10451 0 7915",
            "type": "normal"
        },
        {
            "name": "Bayville",
            "sirenpos": "10204 24 12045",
            "target": "10204 0 12045",
            "type": "normal"
        },
        {
            "name": "Portland",
            "sirenpos": "6323 24 14641",
            "target": "6323 0 14641",
            "type": "normal"
        },
        {
            "name": "North Haven",
            "sirenpos": "1545 24 15545",
            "target": "1545 0 15545",
            "type": "normal"
        },
        {
            "name": "East Harbor",
            "sirenpos": "11443 24 9905",
            "target": "11443 0 9905",
            "type": "normal"
        },
        {
            "name": "Area 42",
            "sirenpos": "13340 24 9953",
            "target": "13340 0 9953",
            "type": "normal"
        }
    ],
    "SubTrajectory": [
        {
            "name": "1",
            "pos": [
                "0 -1 800",
                "3092 -1 985",
                "3676 -1 1677",
                "6491 -1 1599",
                "10310 -1 1319",
                "15500 -1 2500"
            ]
        },
        {
            "name": "2",
            "pos": [
                "3092 -1 985"
            ]
        }
    ],
    "BoatTrajectory": [
        {
            "name": "1",
            "pos": [
                "15323 -1 13495",
                "13981 -1 8879",
                "15272 -1 153"
            ]
        }
    ]
}