<?xml version="1.0" encoding="UTF-8"?>
<territory-type>
    <territory color="2387830984">
        <zone name="InfectedMedic" smin="4" smax="10" dmin="5" dmax="10" x="6088.50" z="14574.73" r="60"/> <!-- Portland -->
        <zone name="InfectedMedic" smin="4" smax="10" dmin="5" dmax="10" x="9857.50" z="10812.56" r="60"/> <!-- Racetrack -->
        <zone name="InfectedMedic" smin="4" smax="10" dmin="5" dmax="10" x="11496.00" z="10142.91" r="60"/> <!-- East Harbor East -->
        <zone name="InfectedMedic" smin="4" smax="10" dmin="5" dmax="10" x="11009.00" z="10342.60" r="60"/> <!-- East Harbor West -->
        <zone name="InfectedMedic" smin="4" smax="10" dmin="5" dmax="10" x="9083.00" z="9361.14" r="60"/> <!-- Waldorboro East -->
        <zone name="InfectedMedic" smin="4" smax="10" dmin="5" dmax="10" x="8293.00" z="9172.96" r="60"/> <!-- Waldoboro West -->
        <zone name="InfectedMedic" smin="4" smax="10" dmin="5" dmax="10" x="6376.00" z="6184.04" r="60"/> <!-- Sunset Cross North -->
        <zone name="InfectedMedic" smin="4" smax="10" dmin="5" dmax="10" x="6946.00" z="5829.69" r="60"/> <!-- Sunset Cross South -->
        <zone name="InfectedMedic" smin="4" smax="10" dmin="5" dmax="10" x="10234.50" z="5011.39" r="60"/> <!-- Oceanville -->
        <zone name="InfectedMedic" smin="4" smax="10" dmin="5" dmax="10" x="9810.50" z="4404.80" r="60"/> <!-- Road to Smallville -->
        <zone name="InfectedMedic" smin="4" smax="10" dmin="5" dmax="10" x="6924.00" z="2070.02" r="60"/> <!-- Stonington -->
        <zone name="InfectedMedic" smin="4" smax="10" dmin="5" dmax="10" x="7261.00" z="1965.92" r="60"/> <!-- Stonington East -->
        <zone name="InfectedMedic" smin="4" smax="10" dmin="5" dmax="10" x="6768.00" z="1524.49" r="60"/> <!-- Stonington Harbor -->
        <zone name="InfectedMedic" smin="4" smax="10" dmin="5" dmax="10" x="5405.00" z="1571.53" r="60"/> <!-- East of Greenville -->
        <zone name="InfectedMedic" smin="4" smax="10" dmin="5" dmax="10" x="5035.50" z="2123.57" r="60"/> <!-- Scout Camp -->
        <zone name="InfectedMedic" smin="4" smax="10" dmin="5" dmax="10" x="4649.00" z="4506.40" r="60"/> <!-- Georgetown -->
        <zone name="InfectedMedic" smin="4" smax="10" dmin="5" dmax="10" x="3124.00" z="4193.09" r="60"/> <!-- Partis Island -->
        <zone name="InfectedMedic" smin="4" smax="10" dmin="5" dmax="10" x="4571.00" z="6968.81" r="60"/> <!-- Power Plant -->
        <zone name="InfectedMedic" smin="4" smax="10" dmin="5" dmax="10" x="5354.00" z="7549.87" r="60"/> <!-- Sandy Bay -->
        <zone name="InfectedMedic" smin="4" smax="10" dmin="5" dmax="10" x="3271.00" z="6373.22" r="60"/> <!-- Westbrook -->
        <zone name="InfectedMedic" smin="4" smax="10" dmin="5" dmax="10" x="1851.50" z="9119.41" r="60"/> <!-- Old Town -->
        <zone name="InfectedMedic" smin="4" smax="10" dmin="5" dmax="10" x="7167.00" z="11631.86" r="60"/> <!-- KMUC -->
    </territory>
    <territory color="1136576269">
        <zone name="InfectedCity" smin="4" smax="10" dmin="10" dmax="20" x="6043.50" z="14720.38" r="60"/> <!-- Portland North -->
        <zone name="InfectedCity" smin="4" smax="10" dmin="10" dmax="20" x="6066.00" z="14143.31" r="60"/> <!-- Portland South -->
        <zone name="InfectedCity" smin="4" smax="10" dmin="10" dmax="20" x="10209.50" z="12069.29" r="60"/> <!-- Bayville -->
        <zone name="InfectedCity" smin="4" smax="10" dmin="10" dmax="20" x="10228.00" z="10922.67" r="60"/> <!-- Racetrack -->
        <zone name="InfectedCity" smin="4" smax="10" dmin="10" dmax="20" x="11554.00" z="10069.83" r="20"/> <!-- East Harbor East -->
        <zone name="InfectedCity" smin="4" smax="10" dmin="10" dmax="20" x="11285.00 " z="10297.06" r="20"/> <!-- East Harbor West -->
        <zone name="InfectedCity" smin="4" smax="10" dmin="10" dmax="20" x="9102.00" z="9501.28" r="60"/> <!-- Waldoboro North -->
        <zone name="InfectedCity" smin="4" smax="10" dmin="10" dmax="20" x="8327.00" z="9329.11" r="60"/> <!-- Waldoboro South -->
        <zone name="InfectedCity" smin="4" smax="10" dmin="10" dmax="20" x="8924.00" z="8844.64" r="60"/> <!-- Waldoboro East -->
        <zone name="InfectedCity" smin="4" smax="10" dmin="10" dmax="20" x="8303.00" z="8871.66" r="60"/> <!-- Waldoboro West -->
        <zone name="InfectedCity" smin="4" smax="10" dmin="10" dmax="20" x="7287.00" z="8469.27" r="60"/> <!-- Mountainville -->
        <zone name="InfectedCity" smin="4" smax="10" dmin="10" dmax="20" x="5374.00" z="7645.47" r="60"/> <!-- Sandy Bay -->
        <zone name="InfectedCity" smin="4" smax="10" dmin="10" dmax="20" x="3224.00" z="6315.17" r="60"/> <!-- Westbrook -->
        <zone name="InfectedCity" smin="4" smax="10" dmin="10" dmax="20" x="3583.00" z="6573.42" r="60"/> <!-- Westbrook North East -->
        <zone name="InfectedCity" smin="4" smax="10" dmin="10" dmax="20" x="3447.00" z="6121.98" r="60"/> <!-- Westbrook South East -->
        <zone name="InfectedCity" smin="4" smax="10" dmin="10" dmax="20" x="1924.00" z="9057.85" r="60"/> <!-- Oldtown -->
        <zone name="InfectedCity" smin="4" smax="10" dmin="10" dmax="20" x="4695.00" z="4446.34" r="60"/> <!-- George Town -->
        <zone name="InfectedCity" smin="4" smax="10" dmin="10" dmax="20" x="4629.00" z="2679.62" r="60"/> <!-- Hazeland -->
        <zone name="InfectedCity" smin="4" smax="10" dmin="10" dmax="20" x="4749.00" z="1514.48" r="60"/> <!-- Greenville -->
        <zone name="InfectedCity" smin="4" smax="10" dmin="10" dmax="20" x="7347.50" z="1509.97" r="60"/> <!-- Stonington Suburb East -->
        <zone name="InfectedCity" smin="4" smax="10" dmin="10" dmax="20" x="7104.00" z="1497.46" r="60"/> <!-- Stonington Suburb West -->
        <zone name="InfectedCity" smin="4" smax="10" dmin="10" dmax="20" x="7054.00" z="2024.48" r="60"/> <!-- Stonington East -->
        <zone name="InfectedCity" smin="4" smax="10" dmin="10" dmax="20" x="6868.00" z="1986.44" r="60"/> <!-- Stonington -->
        <zone name="InfectedCity" smin="4" smax="10" dmin="10" dmax="20" x="6358.00" z="1964.42" r="60"/> <!-- Stongton West -->
        <zone name="InfectedCity" smin="4" smax="10" dmin="10" dmax="20" x="7298.50" z="2623.56" r="60"/> <!-- Ashville -->
        <zone name="InfectedCity" smin="4" smax="10" dmin="10" dmax="20" x="10215.50" z="5027.41" r="60"/> <!-- Oceanville North -->
        <zone name="InfectedCity" smin="4" smax="10" dmin="10" dmax="20" x="10233.50" z="4839.23" r="60"/> <!-- Oceanvill South -->
        <zone name="InfectedCity" smin="4" smax="10" dmin="10" dmax="20" x="7085.50" z="5402.78" r="60"/> <!-- Warren Cove -->
        <zone name="InfectedCity" smin="4" smax="10" dmin="10" dmax="20" x="6613.50" z="6350.20" r="60"/> <!-- Sunset Cross -->
        <zone name="InfectedCity" smin="4" smax="10" dmin="10" dmax="20" x="5416.50" z="7723.54" r="60"/> <!-- Sandy Bay -->
        <zone name="InfectedCity" smin="4" smax="10" dmin="10" dmax="20" x="7268.50" z="8568.37" r="60"/> <!-- Mountainville East -->
        <zone name="InfectedCity" smin="4" smax="10" dmin="10" dmax="20" x="7310.00" z="8437.24" r="60"/> <!-- Mountainville West -->
        <zone name="InfectedCity" smin="4" smax="10" dmin="10" dmax="20" x="10376.50" z="7849.67" r="60"/> <!-- Eastbrook -->
    </territory>
    <territory color="1291845632"/>
    <territory color="1910952871">
        <zone name="InfectedSolitude" smin="4" smax="10" dmin="5" dmax="10" x="10134" z="10632" r="120"/>
        <zone name="InfectedSolitude" smin="4" smax="10" dmin="5" dmax="10" x="10386.2" z="4371.5" r="120"/>
        <zone name="InfectedSolitude" smin="4" smax="10" dmin="5" dmax="10" x="9814.33" z="4478.33" r="120"/>
        <zone name="InfectedSolitude" smin="4" smax="10" dmin="5" dmax="10" x="9494.67" z="3649" r="120"/>
        <zone name="InfectedSolitude" smin="4" smax="10" dmin="5" dmax="10" x="6142" z="13386.3" r="120"/>
        <zone name="InfectedSolitude" smin="4" smax="10" dmin="5" dmax="10" x="9368.67" z="9117.33" r="120"/>
        <zone name="InfectedSolitude" smin="4" smax="10" dmin="5" dmax="10" x="4301" z="4662" r="120"/>
        <zone name="InfectedSolitude" smin="4" smax="10" dmin="5" dmax="10" x="8761.67" z="9169.67" r="120"/>
        <zone name="InfectedSolitude" smin="4" smax="10" dmin="5" dmax="10" x="6300" z="8077" r="120"/>
        <zone name="InfectedSolitude" smin="4" smax="10" dmin="5" dmax="10" x="5445.7" z="7665.81" r="120"/>
        <zone name="InfectedSolitude" smin="4" smax="10" dmin="5" dmax="10" x="6305.71" z="14343" r="120"/>
        <zone name="InfectedSolitude" smin="4" smax="10" dmin="5" dmax="10" x="6620.67" z="6424" r="120"/>
        <zone name="InfectedSolitude" smin="4" smax="10" dmin="5" dmax="10" x="10258.7" z="10857" r="120"/>
        <zone name="InfectedSolitude" smin="4" smax="10" dmin="5" dmax="10" x="6177" z="15025" r="120"/>
        <zone name="InfectedSolitude" smin="4" smax="10" dmin="5" dmax="10" x="9359.33" z="5288" r="120"/>
        <zone name="InfectedSolitude" smin="4" smax="10" dmin="5" dmax="10" x="4681" z="4534" r="120"/>
        <zone name="InfectedSolitude" smin="4" smax="10" dmin="5" dmax="10" x="9681.33" z="4127" r="120"/>
        <zone name="InfectedSolitude" smin="4" smax="10" dmin="5" dmax="10" x="6205.24" z="6909.77" r="120"/>
        <zone name="InfectedSolitude" smin="4" smax="10" dmin="5" dmax="10" x="6174.67" z="13694.3" r="120"/>
        <zone name="InfectedSolitude" smin="4" smax="10" dmin="5" dmax="10" x="6436.5" z="14074.2" r="120"/>
        <zone name="InfectedSolitude" smin="4" smax="10" dmin="5" dmax="10" x="9147.83" z="9491.5" r="120"/>
        <zone name="InfectedSolitude" smin="4" smax="10" dmin="5" dmax="10" x="6230.83" z="9651.83" r="120"/>
        <zone name="InfectedSolitude" smin="4" smax="10" dmin="5" dmax="10" x="9225" z="9795.17" r="120"/>
        <zone name="InfectedSolitude" smin="4" smax="10" dmin="5" dmax="10" x="6049.17" z="14797.5" r="120"/>
        <zone name="InfectedSolitude" smin="4" smax="10" dmin="5" dmax="10" x="9067.17" z="9213.33" r="120"/>
        <zone name="InfectedSolitude" smin="4" smax="10" dmin="5" dmax="10" x="6390.83" z="14823.8" r="120"/>
        <zone name="InfectedSolitude" smin="4" smax="10" dmin="5" dmax="10" x="6055.5" z="14045.7" r="120"/>
        <zone name="InfectedSolitude" smin="4" smax="10" dmin="5" dmax="10" x="8909.67" z="9447.33" r="120"/>
        <zone name="InfectedSolitude" smin="4" smax="10" dmin="5" dmax="10" x="7046.33" z="7157.33" r="120"/>
        <zone name="InfectedSolitude" smin="4" smax="10" dmin="5" dmax="10" x="8423.33" z="4292.33" r="120"/>
        <zone name="InfectedSolitude" smin="4" smax="10" dmin="5" dmax="10" x="5523" z="7257" r="120"/>
        <zone name="InfectedSolitude" smin="4" smax="10" dmin="5" dmax="10" x="7111.67" z="5272.33" r="120"/>
        <zone name="InfectedSolitude" smin="4" smax="10" dmin="5" dmax="10" x="6907.5" z="11415" r="120"/>
        <zone name="InfectedSolitude" smin="4" smax="10" dmin="5" dmax="10" x="3660.42" z="5540.5" r="120"/>
        <zone name="InfectedSolitude" smin="4" smax="10" dmin="5" dmax="10" x="10056.8" z="10807.1" r="120"/>
        <zone name="InfectedSolitude" smin="4" smax="10" dmin="5" dmax="10" x="9758.33" z="5582.25" r="120"/>
        <zone name="InfectedSolitude" smin="4" smax="10" dmin="5" dmax="10" x="6544.17" z="3886.83" r="120"/>
        <zone name="InfectedSolitude" smin="4" smax="10" dmin="5" dmax="10" x="8685.5" z="4219.92" r="120"/>
        <zone name="InfectedSolitude" smin="4" smax="10" dmin="5" dmax="10" x="5156" z="8041" r="120"/>
        <zone name="InfectedSolitude" smin="4" smax="10" dmin="5" dmax="10" x="4665" z="7890" r="120"/>
        <zone name="InfectedSolitude" smin="4" smax="10" dmin="5" dmax="10" x="7219.33" z="4780.33" r="120"/>
        <zone name="InfectedSolitude" smin="4" smax="10" dmin="5" dmax="10" x="5480.33" z="8520" r="120"/>
        <zone name="InfectedSolitude" smin="4" smax="10" dmin="5" dmax="10" x="7413.33" z="8441.33" r="120"/>
        <zone name="InfectedSolitude" smin="4" smax="10" dmin="5" dmax="10" x="6970.67" z="5863.67" r="120"/>
        <zone name="InfectedSolitude" smin="4" smax="10" dmin="5" dmax="10" x="7311.03" z="2565.15" r="120"/>
        <zone name="InfectedSolitude" smin="4" smax="10" dmin="5" dmax="10" x="4950.77" z="2088.55" r="120"/>
        <zone name="InfectedSolitude" smin="4" smax="10" dmin="5" dmax="10" x="4829" z="4411.51" r="120"/>
        <zone name="InfectedSolitude" smin="4" smax="10" dmin="5" dmax="10" x="7249.67" z="8606.67" r="120"/>
        <zone name="InfectedSolitude" smin="4" smax="10" dmin="5" dmax="10" x="6118.67" z="15281.7" r="120"/>
        <zone name="InfectedSolitude" smin="4" smax="10" dmin="5" dmax="10" x="5010.53" z="7063.2" r="110"/>
        <zone name="InfectedSolitude" smin="4" smax="10" dmin="5" dmax="10" x="5893.13" z="9497.17" r="120"/>
        <zone name="InfectedSolitude" smin="4" smax="10" dmin="5" dmax="10" x="4484.29" z="3221.53" r="120"/>
        <zone name="InfectedSolitude" smin="4" smax="10" dmin="5" dmax="10" x="7555.04" z="3897.19" r="120"/>
        <zone name="InfectedSolitude" smin="4" smax="10" dmin="5" dmax="10" x="8545.96" z="5124.19" r="120"/>
        <zone name="InfectedSolitude" smin="4" smax="10" dmin="5" dmax="10" x="10218" z="5452.38" r="120"/>
        <zone name="InfectedSolitude" smin="4" smax="10" dmin="5" dmax="10" x="9032.47" z="5205.37" r="120"/>
        <zone name="InfectedSolitude" smin="4" smax="10" dmin="5" dmax="10" x="4544.62" z="3860" r="120"/>
        <zone name="InfectedSolitude" smin="4" smax="10" dmin="5" dmax="10" x="7447.29" z="3295.07" r="120"/>
        <zone name="InfectedSolitude" smin="4" smax="10" dmin="5" dmax="10" x="5705.04" z="8054.67" r="120"/>
        <zone name="InfectedSolitude" smin="4" smax="10" dmin="5" dmax="10" x="5975" z="8451.47" r="120"/>
        <zone name="InfectedSolitude" smin="4" smax="10" dmin="5" dmax="10" x="5805" z="8308.5" r="120"/>
        <zone name="InfectedSolitude" smin="4" smax="10" dmin="5" dmax="10" x="6201.33" z="13951.5" r="120"/>
        <zone name="InfectedSolitude" smin="4" smax="10" dmin="5" dmax="10" x="10368" z="12008" r="120"/>
        <zone name="InfectedSolitude" smin="2" smax="4" dmin="10" dmax="4" x="3197.33" z="10672" r="120"/>
        <zone name="InfectedSolitude" smin="3" smax="5" dmin="5" dmax="10" x="2720" z="11040" r="120"/>
        <zone name="InfectedSolitude" smin="3" smax="5" dmin="5" dmax="10" x="1656" z="11288" r="120"/>
        <zone name="InfectedSolitude" smin="5" smax="8" dmin="5" dmax="10" x="1546.67" z="12109.3" r="120"/>
        <zone name="InfectedSolitude" smin="5" smax="8" dmin="5" dmax="10" x="1490.67" z="11904" r="120"/>
        <zone name="InfectedSolitude" smin="3" smax="6" dmin="5" dmax="10" x="1864" z="12157.3" r="120"/>
        <zone name="InfectedSolitude" smin="2" smax="3" dmin="5" dmax="10" x="530.667" z="12290.7" r="120"/>
        <zone name="InfectedSolitude" smin="2" smax="4" dmin="10" dmax="4" x="2504" z="13970.7" r="120"/>
        <zone name="InfectedSolitude" smin="1" smax="2" dmin="5" dmax="10" x="2229.33" z="14085.3" r="120"/>
        <zone name="InfectedSolitude" smin="4" smax="6" dmin="5" dmax="10" x="3058.67" z="13480" r="120"/>
        <zone name="InfectedSolitude" smin="4" smax="6" dmin="5" dmax="10" x="3432" z="13632" r="120"/>
        <zone name="InfectedSolitude" smin="3" smax="5" dmin="5" dmax="10" x="3661.33" z="13557.3" r="120"/>
    </territory>
    <territory color="1291845632">
        <zone name="InfectedReligious" smin="4" smax="10" dmin="5" dmax="10" x="6303.00" z="14702.36" r="60"/> <!-- Portland North -->
        <zone name="InfectedReligious" smin="4" smax="10" dmin="5" dmax="10" x="6317.00" z="14585.24" r="60"/> <!-- Portland South -->
        <zone name="InfectedReligious" smin="4" smax="10" dmin="5" dmax="10" x="10464.00" z="11369.10" r="60"/> <!-- Racetrack Hills -->
        <zone name="InfectedReligious" smin="4" smax="10" dmin="5" dmax="10" x="11339.00" z="10287.05" r="60"/> <!-- East Harbor East -->
        <zone name="InfectedReligious" smin="4" smax="10" dmin="5" dmax="10" x="11291.50" z="10284.04" r="60"/> <!-- East Harbor West -->
        <zone name="InfectedReligious" smin="4" smax="10" dmin="5" dmax="10" x="8788.00" z="9141.43" r="20"/> <!-- Waldoboro -->
        <zone name="InfectedReligious" smin="4" smax="10" dmin="8" dmax="10" x="9340.00" z="8046.86" r="20"/> <!-- Montville -->
        <zone name="InfectedReligious" smin="4" smax="10" dmin="25" dmax="40" x="9791.00" z="5437.31" r="20"/> <!-- Scout Camp Island -->
        <zone name="InfectedReligious" smin="4" smax="10" dmin="5" dmax="10" x="8368.00" z="2197.15" r="60"/> <!-- East of Stonington -->
        <zone name="InfectedReligious" smin="4" smax="10" dmin="5" dmax="10" x="6148.00" z="1741.70" r="60"/> <!-- West of Stonington -->
        <zone name="InfectedReligious" smin="4" smax="10" dmin="5" dmax="10" x="7026.00" z="1485.45" r="60"/> <!-- South Suburbs -->
        <zone name="InfectedReligious" smin="4" smax="10" dmin="5" dmax="10" x="4127.50" z="2888.82" r="60"/> <!-- Hazeland -->
        <zone name="InfectedReligious" smin="4" smax="10" dmin="5" dmax="10" x="4886.00" z="4263.16" r="60"/> <!-- Georgetown -->
        <zone name="InfectedReligious" smin="4" smax="10" dmin="5" dmax="10" x="4517.00" z="7924.24" r="60"/> <!-- North of Power Plant -->
        <zone name="InfectedReligious" smin="4" smax="10" dmin="5" dmax="10" x="3611.00" z="8894.69" r="60"/> <!-- Swamp -->
    </territory>
    <territory color="1794965508">
        <zone name="InfectedPolice" smin="4" smax="10" dmin="5" dmax="10" x="6091.00" z="14740.40" r="60"/> <!-- Portland -->
        <zone name="InfectedPolice" smin="4" smax="10" dmin="5" dmax="10" x="10113.00" z="10962.71" r="60"/> <!-- Racetrack -->
        <zone name="InfectedPolice" smin="4" smax="10" dmin="5" dmax="10" x="11380.50" z="10133.90" r="60"/> <!-- East Harbor -->
        <zone name="InfectedPolice" smin="4" smax="10" dmin="5" dmax="10" x="9021.00" z="8831.62" r="60"/> <!-- Waldoboro East -->
        <zone name="InfectedPolice" smin="4" smax="10" dmin="5" dmax="10" x="8339.00" z="8710.51" r="60"/> <!-- Waldoboro West -->
        <zone name="InfectedPolice" smin="4" smax="10" dmin="5" dmax="10" x="10376.00" z="8007.32" r="60"/> <!-- Eastbrook -->
        <zone name="InfectedPolice" smin="4" smax="10" dmin="5" dmax="10" x="9770.50" z="4333.23" r="60"/> <!-- Road to Smallville -->
        <zone name="InfectedPolice" smin="4" smax="10" dmin="5" dmax="10" x="7090.00" z="1932.89" r="60"/> <!-- Stonington East -->
        <zone name="InfectedPolice" smin="4" smax="10" dmin="5" dmax="10" x="6423.00" z="2057.01" r="60"/> <!-- Stonington West -->
        <zone name="InfectedPolice" smin="4" smax="10" dmin="5" dmax="10" x="7008.00" z="1562.53" r="60"/> <!-- South Suburbs -->
        <zone name="InfectedPolice" smin="4" smax="10" dmin="5" dmax="10" x="4409.00" z="2844.78" r="60"/> <!-- Hazeland -->
        <zone name="InfectedPolice" smin="4" smax="10" dmin="5" dmax="10" x="5463.00" z="3894.30" r="60"/> <!-- Airfield -->
        <zone name="InfectedPolice" smin="4" smax="10" dmin="5" dmax="10" x="4641.50" z="4400.30" r="60"/> <!-- Georgetown -->
        <zone name="InfectedPolice" smin="4" smax="10" dmin="5" dmax="10" x="7109.50" z="5441.31" r="60"/> <!-- Warren Cove -->
        <zone name="InfectedPolice" smin="4" smax="10" dmin="5" dmax="10" x="3269.00" z="6539.89" r="60"/> <!-- Westbook North -->
        <zone name="InfectedPolice" smin="4" smax="10" dmin="5" dmax="10" x="3289.50" z="6249.60" r="60"/> <!-- Westbrook South -->
        <zone name="InfectedPolice" smin="4" smax="10" dmin="5" dmax="10" x="5386.50" z="7582.40" r="60"/> <!-- Sandy Bay -->
        <zone name="InfectedPolice" smin="4" smax="10" dmin="5" dmax="10" x="3725.00" z="8657.45" r="60"/> <!-- Swamp -->
        <zone name="InfectedPolice" smin="4" smax="10" dmin="5" dmax="10" x="2059.00" z="9085.37" r="60"/> <!-- Old Town East -->
        <zone name="InfectedPolice" smin="4" smax="10" dmin="5" dmax="10" x="1648.00" z="9023.81" r="60"/> <!-- Old Town West -->
    </territory>
    <territory color="1102461653">
        <zone name="InfectedIndustrial" smin="4" smax="10" dmin="5" dmax="10" x="5752.00" z="14911.56" r="60"/> <!-- Portland North -->
        <zone name="InfectedIndustrial" smin="4" smax="10" dmin="5" dmax="10" x="5805.00" z="14515.18" r="60"/> <!-- Portland South -->
        <zone name="InfectedIndustrial" smin="4" smax="10" dmin="5" dmax="10" x="9967.00" z="11032.77" r="60"/> <!-- Racetrack -->
        <zone name="InfectedIndustrial" smin="4" smax="10" dmin="5" dmax="10" x="11551.00" z="10066.33" r="60"/> <!-- East Bay -->
        <zone name="InfectedIndustrial" smin="4" smax="10" dmin="5" dmax="10" x="9169.50" z="9361.64" r="60"/> <!-- Waldoboro -->
        <zone name="InfectedIndustrial" smin="4" smax="10" dmin="5" dmax="10" x="10749.00" z="3187.11" r="20"/> <!-- Crotch Island North-->
        <zone name="InfectedIndustrial" smin="4" smax="10" dmin="5" dmax="10" x="10993.00" z="2291.24" r="60"/> <!-- Crotch Island Mine -->
        <zone name="InfectedIndustrial" smin="4" smax="10" dmin="5" dmax="10" x="8664.00" z="3518.94" r="60"/> <!-- Rando Island -->
        <zone name="InfectedIndustrial" smin="4" smax="10" dmin="5" dmax="10" x="6926.00" z="2317.26" r="60"/> <!-- Stonington Industrial East -->
        <zone name="InfectedIndustrial" smin="4" smax="10" dmin="5" dmax="10" x="6682.00" z="2339.28" r="60"/> <!-- Stonington Industrial West -->
        <zone name="InfectedIndustrial" smin="4" smax="10" dmin="5" dmax="10" x="6571.00" z="1906.86" r="60"/> <!-- Stonington West -->
        <zone name="InfectedIndustrial" smin="4" smax="10" dmin="5" dmax="10" x="6984.50" z="1315.78" r="20"/> <!-- Stonington Harbor East -->
        <zone name="InfectedIndustrial" smin="4" smax="10" dmin="5" dmax="10" x="6637.50" z="1394.86" r="20"/> <!-- Stonington Harbor West -->
        <zone name="InfectedIndustrial" smin="4" smax="10" dmin="5" dmax="10" x="4440.50" z="2766.20" r="60"/> <!-- Hazeland -->
        <zone name="InfectedIndustrial" smin="4" smax="10" dmin="5" dmax="10" x="3843.00" z="2557.50" r="60"/> <!-- Hazeland Harbor West -->
        <zone name="InfectedIndustrial" smin="4" smax="10" dmin="5" dmax="10" x="4698.00" z="6984.82" r="60"/> <!-- Power Plant South -->
        <zone name="InfectedIndustrial" smin="4" smax="10" dmin="5" dmax="10" x="4577.00" z="7177.01" r="60"/> <!-- Power Pland North -->
        <zone name="InfectedIndustrial" smin="4" smax="10" dmin="5" dmax="10" x="4820.00" z="7065.90" r="60"/> <!-- Power Plant Central -->
        <zone name="InfectedIndustrial" smin="4" smax="10" dmin="5" dmax="10" x="5094.00" z="9215.50" r="60"/> <!-- Bridge to QuickStop -->
        <zone name="InfectedIndustrial" smin="4" smax="10" dmin="5" dmax="10" x="2340.00" z="8665.46" r="60"/> <!-- Old Town -->
        <zone name="InfectedIndustrial" smin="4" smax="10" dmin="5" dmax="10" x="4456.00" z="11971.19" r="60"/> <!-- Woodworking South -->
        <zone name="InfectedIndustrial" smin="4" smax="10" dmin="5" dmax="10" x="4482.50" z="12035.25" r="60"/> <!-- Woodworking Central -->
        <zone name="InfectedIndustrial" smin="4" smax="10" dmin="5" dmax="10" x="4502.00" z="12211.43" r="60"/> <!-- Woodworking North -->
        <zone name="InfectedIndustrial" smin="4" smax="10" dmin="5" dmax="10" x="7181.00" z="11688.92" r="60"/> <!-- KUMC -->
        <zone name="InfectedIndustrial" smin="4" smax="10" dmin="5" dmax="10" x="12954.00" z="10070.83" r="20"/> <!-- Area 42 -->
        <zone name="InfectedIndustrial" smin="4" smax="10" dmin="5" dmax="10" x="3837.00" z="8802.60" r="60"/> <!-- Swamp -->
        <zone name="InfectedIndustrial" smin="4" smax="10" dmin="5" dmax="10" x="487.00" z="15300.94" r="60"/> <!-- North Haven Harbor North -->
        <zone name="InfectedIndustrial" smin="4" smax="10" dmin="5" dmax="10" x="693.00" z="14936.59" r="60"/> <!-- North Haven Harbor South -->
    </territory>
    <territory color="1790009876">
        <zone name="InfectedFirefighter" smin="4" smax="10" dmin="5" dmax="10" x="6156.00" z="14153.8" r="60"/> <!-- Portland -->
        <zone name="InfectedFirefighter" smin="4" smax="10" dmin="5" dmax="10" x="10032.00" z="11058.80" r="60"/> <!-- Racetrack -->
        <zone name="InfectedFirefighter" smin="4" smax="10" dmin="5" dmax="10" x="9272.00" z="9453.23" r="60"/> <!-- Waldoboro -->
        <zone name="InfectedFirefighter" smin="4" smax="10" dmin="5" dmax="10" x="10184.00" z="5012.90" r="60"/> <!-- Oceanville -->
        <zone name="InfectedFirefighter" smin="4" smax="10" dmin="5" dmax="10" x="10616.00" z="3107.03" r="60"/> <!-- Crotch Island -->
        <zone name="InfectedFirefighter" smin="4" smax="10" dmin="5" dmax="10" x="7037.00" z="1930.89" r="60"/> <!-- Stonington -->
        <zone name="InfectedFirefighter" smin="4" smax="10" dmin="5" dmax="10" x="6384.00" z="1349.32" r="60"/> <!-- South Suburbs -->
        <zone name="InfectedFirefighter" smin="4" smax="10" dmin="5" dmax="10" x="4540.00" z="2781.72" r="60"/> <!-- Hazeland -->
        <zone name="InfectedFirefighter" smin="4" smax="10" dmin="5" dmax="10" x="4646.00" z="4614.51" r="60"/> <!-- Georgetown -->
        <zone name="InfectedFirefighter" smin="4" smax="10" dmin="5" dmax="10" x="2967.00" z="3801.71" r="60"/> <!-- Paris Island -->
        <zone name="InfectedFirefighter" smin="4" smax="10" dmin="5" dmax="10" x="3360.00" z="6506.35" r="60"/> <!-- Westbrook North -->
        <zone name="InfectedFirefighter" smin="4" smax="10" dmin="5" dmax="10" x="3259.00" z="6316.17" r="60"/> <!-- Westbrook South -->
        <zone name="InfectedFirefighter" smin="4" smax="10" dmin="5" dmax="10" x="4462.00" z="7216.05" r="60"/> <!-- Powerplant -->
        <zone name="InfectedFirefighter" smin="4" smax="10" dmin="5" dmax="10" x="5477.00" z="7748.57" r="60"/> <!-- Sandy Bay -->
    </territory>
    <territory color="1124502272">
        <zone name="InfectedArmy" smin="4" smax="8" dmin="5" dmax="20" x="6092.00" z="14624.28" r="20"/> <!-- Portland -->
        <zone name="InfectedArmy" smin="4" smax="8" dmin="20" dmax="20" x="7169.00" z="11627.35" r="20"/> <!-- KUMC -->
        <zone name="InfectedArmy" smin="4" smax="8" dmin="5" dmax="20" x="9905.00" z="10933.68" r="60"/> <!-- Racetrack -->
        <zone name="InfectedArmy" smin="4" smax="8" dmin="5" dmax="20" x="11293.50" z="10061.83" r="20"/> <!-- East Bay West -->
        <zone name="InfectedArmy" smin="4" smax="8" dmin="5" dmax="20" x="11451.00" z="10198.96" r="20"/> <!-- East Bay East -->
        <zone name="InfectedArmy" smin="4" smax="8" dmin="10" dmax="20" x="13494.00" z="9969.74" r="20"/> <!-- Area 42 North North East -->
        <zone name="InfectedArmy" smin="4" smax="8" dmin="10" dmax="20" x="13695.00" z="9882.65" r="20"/> <!-- Area 42 North East -->
        <zone name="InfectedArmy" smin="4" smax="8" dmin="10" dmax="20" x="13278.00" z="9785.56" r="20"/> <!-- Area 42 Central -->
        <zone name="InfectedArmy" smin="4" smax="8" dmin="10" dmax="20" x="13082.00" z="9901.67" r="20"/> <!-- Area 42 West -->
        <zone name="InfectedArmy" smin="4" smax="8" dmin="10" dmax="20" x="13451.00" z="9671.44" r="20"/> <!-- Area 42 Airstrip -->
        <zone name="InfectedArmy" smin="4" smax="8" dmin="5" dmax="20" x="14247.00" z="6455.30" r="20"/> <!-- Abandoned Sunken City West -->
        <zone name="InfectedArmy" smin="4" smax="8" dmin="5" dmax="20" x="14324.00" z="6390.74" r="20"/> <!-- Abandoned Sunken City East -->
        <zone name="InfectedArmy" smin="4" smax="8" dmin="10" dmax="20" x="14574.50" z="5275.65" r="20"/> <!-- Abandoned East Island -->
        <zone name="InfectedArmy" smin="4" smax="8" dmin="10" dmax="20" x="14381.00" z="5257.13" r="20"/> <!-- Abandoned East Island -->
        <zone name="InfectedArmy" smin="4" smax="8" dmin="10" dmax="20" x="10882.00" z="2307.25" r="20"/> <!-- Mine -->
        <zone name="InfectedArmy" smin="4" smax="8" dmin="20" dmax="20" x="8835.00" z="3801.71" r="20"/> <!-- No Name Island Military Camp East -->
        <zone name="InfectedArmy" smin="4" smax="8" dmin="5" dmax="20" x="8717.00" z="3490.41" r="20"/> <!-- No Name Island Harbor -->
        <zone name="InfectedArmy" smin="4" smax="8" dmin="10" dmax="20" x="6803.50" z="2112.56" r="20"/> <!-- Stonington North -->
        <zone name="InfectedArmy" smin="4" smax="8" dmin="5" dmax="20" x="6874.00" z="1749.71" r="20"/> <!-- Stonington South -->
        <zone name="InfectedArmy" smin="4" smax="8" dmin="10" dmax="20" x="5472.00" z="1050.53" r="20"/> <!-- Prison Bridge -->
        <zone name="InfectedArmy" smin="4" smax="8" dmin="10" dmax="20" x="5365.50" z="668.15" r="20"/> <!-- Prison Island West-->
        <zone name="InfectedArmy" smin="4" smax="8" dmin="10" dmax="20" x="5555.50" z="643.63" r="20"/> <!-- Prison Island East -->
        <zone name="InfectedArmy" smin="4" smax="8" dmin="5" dmax="20" x="3849.50" z="2641.58" r="20"/> <!-- Hazeland Harbor -->
        <zone name="InfectedArmy" smin="4" smax="8" dmin="5" dmax="20" x="5141.00" z="3175.10" r="20"/> <!-- Airstrip West -->
        <zone name="InfectedArmy" smin="4" smax="8" dmin="5" dmax="20" x="5589.00" z="3388.31" r="20"/> <!-- Airstrip South -->
        <zone name="InfectedArmy" smin="4" smax="8" dmin="20" dmax="20" x="5491.00" z="3674.59" r="40"/> <!-- Airstrip -->
        <zone name="InfectedArmy" smin="4" smax="8" dmin="5" dmax="20" x="5491.00" z="3838.75" r="20"/> <!-- Airstrip North -->
        <zone name="InfectedArmy" smin="4" smax="8" dmin="10" dmax="20" x="2477.00" z="3355.28" r="20"/> <!-- Paris Island South West -->
        <zone name="InfectedArmy" smin="4" smax="8" dmin="20" dmax="30" x="2932.00" z="3553.47" r="20"/> <!-- Paris Island -->
        <zone name="InfectedArmy" smin="4" smax="8" dmin="10" dmax="20" x="3064.00" z="4066.97" r="20"/> <!-- Paris Island North -->
        <zone name="InfectedArmy" smin="4" smax="8" dmin="10" dmax="20" x="2595.00" z="4305.20" r="20"/> <!-- Paris Island West -->
        <zone name="InfectedArmy" smin="4" smax="8" dmin="5" dmax="20" x="3717.00" z="6218.07" r="20"/> <!-- Westbrook -->
        <zone name="InfectedArmy" smin="4" smax="8" dmin="5" dmax="20" x="4600.00" z="6976.81" r="20"/> <!-- Power Plant South West -->
        <zone name="InfectedArmy" smin="4" smax="8" dmin="5" dmax="20" x="4644.00" z="7169.00" r="20"/> <!-- Power Plant North -->
        <zone name="InfectedArmy" smin="4" smax="8" dmin="5" dmax="20" x="4936.00" z="7083.92" r="20"/> <!-- Power Plant East -->
        <zone name="InfectedArmy" smin="4" smax="8" dmin="10" dmax="20" x="6643.00" z="6858.20" r="40"/> <!-- Oldfield East -->
        <zone name="InfectedArmy" smin="4" smax="8" dmin="10" dmax="20" x="9087.00" z="5953.81" r="20"/> <!-- Scout Camp Island North East -->
        <zone name="InfectedArmy" smin="4" smax="8" dmin="5" dmax="20" x="8880.00" z="5989.85" r="20"/> <!-- Scout Camp Island North -->
        <zone name="InfectedArmy" smin="4" smax="8" dmin="10" dmax="20" x="8578.00" z="6051.91" r="20"/> <!-- Scout Camp Island West -->
        <zone name="InfectedArmy" smin="4" smax="8" dmin="10" dmax="20" x="3731.50" z="8690.99" r="20"/> <!-- Swamp South -->
        <zone name="InfectedArmy" smin="4" smax="8" dmin="20" dmax="30" x="3723.00" z="8845.64" r="20"/> <!-- Swamp -->
        <zone name="InfectedArmy" smin="4" smax="8" dmin="10" dmax="20" x="3557.50" z="8878.17" r="20"/> <!-- Swamp West -->
        <zone name="InfectedArmy" smin="4" smax="8" dmin="5" dmax="20" x="1838.00" z="9339.12" r="20"/> <!-- Old Town -->
        <zone name="InfectedArmy" smin="4" smax="8" dmin="20" dmax="20" x="1520.00" z="15551.19" r="20"/> <!-- Swans Island -->
        <zone name="InfectedArmy" smin="4" smax="8" dmin="5" dmax="20" x="12489.00" z="7669.49" r="20"/> <!-- East of Eastbrook -->
    </territory>
    <territory color="2809946700">
        <zone name="InfectedVillage" smin="4" smax="10" dmin="2" dmax="10" x="6018.50" z="15223.37" r="40"/> <!-- Portland North -->
        <zone name="InfectedVillage" smin="4" smax="10" dmin="2" dmax="10" x="10437.00" z="12023.74" r="40"/> <!-- Bayville -->
        <zone name="InfectedVillage" smin="4" smax="10" dmin="2" dmax="10" x="9672.00" z="9660.43" r="40"/> <!-- Waldoboro East -->
        <zone name="InfectedVillage" smin="4" smax="10" dmin="2" dmax="10" x="9018.00" z="9815.59" r="40"/> <!-- Waldoboro North -->
        <zone name="InfectedVillage" smin="4" smax="10" dmin="2" dmax="10" x="8966.00" z="9134.92" r="40"/> <!-- Waldoboro -->
        <zone name="InfectedVillage" smin="4" smax="10" dmin="2" dmax="10" x="9066.00" z="7771.59" r="40"/> <!-- Threepwood -->
        <zone name="InfectedVillage" smin="4" smax="10" dmin="2" dmax="10" x="9976.00" z="6820.66" r="40"/> <!-- Fiarfield -->
        <zone name="InfectedVillage" smin="4" smax="10" dmin="2" dmax="10" x="9360.00" z="8068.88" r="40"/> <!-- Montville -->
        <zone name="InfectedVillage" smin="4" smax="10" dmin="2" dmax="10" x="6086.00" z="6916.75" r="40"/> <!-- Oldfield -->
        <zone name="InfectedVillage" smin="4" smax="10" dmin="2" dmax="10" x="6426.00" z="6382.23" r="40"/> <!-- Sunset Cross -->
        <zone name="InfectedVillage" smin="4" smax="10" dmin="2" dmax="10" x="6982.00" z="5369.24" r="40"/> <!-- Warren Cove -->
        <zone name="InfectedVillage" smin="4" smax="10" dmin="2" dmax="10" x="7496.00" z="3771.68" r="40"/> <!-- Kushville -->
        <zone name="InfectedVillage" smin="4" smax="10" dmin="2" dmax="10" x="7308.00" z="2392.34" r="40"/> <!-- Ashville -->
        <zone name="InfectedVillage" smin="4" smax="10" dmin="20" dmax="20" x="8268.00" z="1805.76" r="60"/> <!-- East of Stonington -->
        <zone name="InfectedVillage" smin="4" smax="10" dmin="2" dmax="10" x="6262.00" z="2238.19" r="40"/> <!-- Stonington North West -->
        <zone name="InfectedVillage" smin="4" smax="10" dmin="10" dmax="20" x="5383.00" z="1581.54" r="40"/> <!-- East of Greenville -->
        <zone name="InfectedVillage" smin="4" smax="10" dmin="10" dmax="20" x="4682.00" z="2572.51" r="40"/> <!-- Hazeland -->
        <zone name="InfectedVillage" smin="4" smax="10" dmin="2" dmax="10" x="6528.00" z="3887.80" r="40"/> <!-- Milo -->
        <zone name="InfectedVillage" smin="4" smax="10" dmin="10" dmax="20" x="4426.00" z="4299.20" r="40"/> <!-- Georgetown -->
        <zone name="InfectedVillage" smin="4" smax="10" dmin="10" dmax="20" x="3366.00" z="6991.83" r="40"/> <!-- North of Westbrook -->
        <zone name="InfectedVillage" smin="4" smax="10" dmin="2" dmax="10" x="2462.00" z="8976.77" r="40"/> <!-- East of Old Town -->
        <zone name="InfectedVillage" smin="4" smax="10" dmin="2" dmax="10" x="4314.00" z="12029.75" r="40"/> <!-- Woodworking Industrial -->
        <zone name="InfectedVillage" smin="4" smax="10" dmin="2" dmax="10" x="6436.00" z="8468.27" r="40"/> <!-- West of Mountainville -->
        <zone name="InfectedVillage" smin="4" smax="10" dmin="2" dmax="10" x="2028.00" z="12324.04" r="40"/> <!-- North West Islands South -->
        <zone name="InfectedVillage" smin="4" smax="10" dmin="2" dmax="10" x="3729.00" z="13620.30" r="40"/> <!-- North West Islands East -->
        <zone name="InfectedVillage" smin="4" smax="10" dmin="2" dmax="10" x="3046.00" z="13486.17" r="40"/> <!-- North West Islands West -->
        <zone name="InfectedVillage" smin="4" smax="10" dmin="2" dmax="10" x="2660.00" z="14716.37" r="40"/> <!-- North West Islands North -->
        <zone name="InfectedVillage" smin="4" smax="10" dmin="2" dmax="10" x="14256.00" z="5407.28" r="40"/> <!-- Abandoned Fishing Village -->
    </territory>
    <territory color="1289674462"/>
</territory-type>
